dubSplitter/__init__.py
dubSplitter/constants.py
dubSplitter/dubSplitter.py
dubSplitter/functions/__init__.py
dubSplitter/functions/exitWithInfo.py
dubSplitter/functions/output.py
dubSplitter/functions/path.py
dubSplitter/functions/slicer.py
dubSplitter/functions/stringEx.py
dubSplitter/functions/voiceRecognition.py
DubSplitter-0.7.0.dist-info/METADATA
DubSplitter-0.7.0.dist-info/WHEEL
DubSplitter-0.7.0.dist-info/entry_points.txt
DubSplitter-0.7.0.dist-info/top_level.txt
DubSplitter-0.7.0.dist-info/RECORD
