Metadata-Version: 2.1
Name: DubSplitter
Version: 0.7.0
Summary: an easy tool to split dubs based on given silence
Home-page: https://github.com/defisym/HibiscusAVGEngine/tree/main/Utilities/DubSplitter
Author: defisym
Author-email: defisym@outlook.com
License: MIT
Keywords: DubSplitter dub splitter Hibiscus AVG Galgame VisualNovel VN
Classifier: Development Status :: 4 - Beta
Classifier: Environment :: Console
Classifier: Environment :: GPU :: NVIDIA CUDA :: 11.7
Classifier: License :: OSI Approved :: MIT License
Classifier: Natural Language :: English
Classifier: Operating System :: OS Independent
Classifier: Programming Language :: Python :: 3.10
Requires-Dist: sympy
Requires-Dist: pydub
Requires-Dist: openai-whisper
Requires-Dist: colorama
